bin/.bash_profile
bin/DataGenerate_SineWave.py
bin/Data_CSV.py
bin/__init__.py
bin/converter.py
bin/csvformatter.py
bin/gen_nyse_dates.py
bin/investors_report.py
bin/sinewave_data_generator.py
pftk/__init__.py
pftk/pftkfeat/__init__.py
pftk/pftkfeat/classes.py
pftk/pftkfeat/features.py
pftk/pftkfeat/featutil.py
pftk/pftklearn/1knn.py
pftk/pftklearn/__init__.py
pftk/pftklearn/fastknn.py
pftk/pftklearn/gendata.py
pftk/pftklearn/hmm.py
pftk/pftklearn/kdtknn.py
pftk/pftklearn/mldiagnostics.py
pftk/pftklearn/parallelknn.py
pftk/pftksim/__init__.py
pftk/pftksim/tradesim.py
pftk/pftksim/tests/__init__.py
pftk/pftksim/tests/test_tradesim.py
pftk/pftksim/tests/test_tradesim_SPY.py
pftk/pftksim/tests/test_tradesim_SPY_Short.py
pftk/pftkstrat/__init__.py
pftk/pftkstrat/strategies.py
pftk/pftkstudy/__init__.py
pftk/pftkstudy/event_profiler.py
pftk/pftkstudy/events.py
pftk/pftkstudy/sp500.txt
pftk/pftkstudy/study.py
pftk/pftkstudy/symbol-set1.txt
pftk/pftkstudy/symbol-set2.txt
pftk/pftktest/__init__.py
pftk/pftktest/data-classification-prob.csv
pftk/pftktest/data-ripple-prob.csv
pftk/pftktest/testDataAccess.py
pftk/pftktest/testLearner.py
pftk/pftktools/.gitignore
pftk/pftktools/EODHistoricalDataPull.py
pftk/pftktools/YahooDataPull.py
pftk/pftktools/__init__.py
pftk/pftktools/csv2fund.py
pftk/pftktools/report.py
pftk/pftkutil/NYSE_dates.txt
pftk/pftkutil/__init__.py
pftk/pftkutil/data_access.py
pftk/pftkutil/fundutil.py
pftk/pftkutil/graph.png
pftk/pftkutil/qsdateutil.py
pftk/pftkutil/report.html
pftk/pftkutil/tsutil.py
pftk/pftkutil/utils.py
pftk/pftkutil/tests/__init__.py
pftk/pftkutil/tests/test_utils.py
pftk-0.5.2.dev0.dist-info/LICENSE.md
pftk-0.5.2.dev0.dist-info/METADATA
pftk-0.5.2.dev0.dist-info/WHEEL
pftk-0.5.2.dev0.dist-info/top_level.txt
pftk-0.5.2.dev0.dist-info/RECORD
