Metadata-Version: 2.1
Name: pftk
Version: 0.5.2.dev0
Summary: Python-based open source software framework designed to support portfolio construction and management.
Home-page: 
Author: Charles Gagnon
Author-email: charlesg@unixrealm.com
License: New BSD
Keywords: finance sharpe portfolio allocation returns
Classifier: Development Status :: 5 - Production/Stable
Classifier: Environment :: Console
Classifier: Intended Audience :: Developers
Classifier: Intended Audience :: Education
Classifier: Intended Audience :: Science/Research
Classifier: Intended Audience :: Financial and Insurance Industry
Classifier: License :: OSI Approved :: BSD License
Classifier: Natural Language :: English
Classifier: Operating System :: MacOS :: MacOS X
Classifier: Operating System :: Microsoft :: Windows
Classifier: Operating System :: POSIX
Classifier: Programming Language :: Python :: 3
Classifier: Topic :: Utilities
License-File: LICENSE.md
Requires-Dist: numpy (>=1.6.1)
Requires-Dist: scipy (>=0.9.0)
Requires-Dist: matplotlib (>=1.1.0)
Requires-Dist: pandas (>=0.7.3)
Requires-Dist: python-dateutil (>=1.5)
Requires-Dist: scikit-learn (>=0.11)
